{
    "$schema": "https://schema.management.azure.com/schemas/2019-04-01/deploymentTemplate.json#",
    "contentVersion": "1.0.0.0",
    "parameters": {
        "baseTemplatePath": {
            "type": "string",
            "metadata": {
                "description": "description"
            }
        }
    },
    "functions": [],
    "variables": {},
    "resources": [
        {
            "name": "logicapp-generatesastoken-deployment",
            "type": "Microsoft.Resources/deployments",
            "apiVersion": "2019-10-01",
            "properties": {
                "mode": "Incremental",
                "templateLink": {
                    "uri": "[uri(parameters('baseTemplatePath'), 'logicapps/generatesastoken.json')]",
                    "contentVersion": "1.0.0.0"
                },
                "parameters": {
                }
            },
            "dependsOn": [
            ]
        }
    ],
    "outputs": {        
    }
}